{".class":"MypyFile","_fullname":"squarecloud.utils","future_import_flags":[],"is_partial_stub_package":false,"is_stub":false,"names":{".class":"SymbolTable","Any":{".class":"SymbolTableNode","cross_ref":"typing.Any","kind":"Gdef","module_hidden":true,"module_public":false},"ConfigFile":{".class":"SymbolTableNode","kind":"Gdef","node":{".class":"TypeInfo","_promote":[],"abstract_attributes":[],"alt_promote":null,"bases":["builtins.object"],"dataclass_transform_spec":null,"declared_metaclass":null,"defn":{".class":"ClassDef","fullname":"squarecloud.utils.ConfigFile","name":"ConfigFile","type_vars":[]},"deletable_attributes":[],"flags":[],"fullname":"squarecloud.utils.ConfigFile","has_param_spec_type":false,"metaclass_type":null,"metadata":{},"module_name":"squarecloud.utils","mro":["squarecloud.utils.ConfigFile","builtins.object"],"names":{".class":"SymbolTable","__init__":{".class":"SymbolTableNode","kind":"Mdef","node":{".class":"Decorator","func":{".class":"FuncDef","abstract_status":0,"arg_kinds":[0,0,0,0,1,1,1,1,1],"arg_names":["self","display_name","main","memory","version","description","subdomain","start","auto_restart"],"dataclass_transform_spec":null,"flags":["is_decorated"],"fullname":"squarecloud.utils.ConfigFile.__init__","name":"__init__","type":{".class":"CallableType","arg_kinds":[0,0,0,0,1,1,1,1,1],"arg_names":["self","display_name","main","memory","version","description","subdomain","start","auto_restart"],"arg_types":["squarecloud.utils.ConfigFile","builtins.str","builtins.str","builtins.int",{".class":"UnionType","items":[{".class":"LiteralType","fallback":"builtins.str","value":"recommended"},{".class":"LiteralType","fallback":"builtins.str","value":"latest"}],"uses_pep604_syntax":false},{".class":"UnionType","items":["builtins.str",{".class":"NoneType"}],"uses_pep604_syntax":true},{".class":"UnionType","items":["builtins.str",{".class":"NoneType"}],"uses_pep604_syntax":true},{".class":"UnionType","items":["builtins.str",{".class":"NoneType"}],"uses_pep604_syntax":true},"builtins.bool"],"bound_args":[],"def_extras":{"first_arg":"self"},"fallback":"builtins.function","from_concatenate":false,"implicit":false,"imprecise_arg_kinds":false,"is_ellipsis_args":false,"name":"__init__ of ConfigFile","ret_type":{".class":"NoneType"},"type_guard":null,"type_is":null,"unpack_kwargs":false,"variables":[]}},"is_overload":false,"var":{".class":"Var","flags":["is_initialized_in_class","is_ready","is_inferred"],"fullname":"squarecloud.utils.ConfigFile.__init__","name":"__init__","type":{".class":"UnionType","items":[{".class":"CallableType","arg_kinds":[2,4],"arg_names":[null,null],"arg_types":[{".class":"AnyType","missing_import_name":null,"source_any":null,"type_of_any":2},{".class":"AnyType","missing_import_name":null,"source_any":null,"type_of_any":2}],"bound_args":[],"def_extras":{},"fallback":"builtins.function","from_concatenate":false,"implicit":false,"imprecise_arg_kinds":false,"is_ellipsis_args":true,"name":null,"ret_type":{".class":"AnyType","missing_import_name":null,"source_any":null,"type_of_any":2},"type_guard":null,"type_is":null,"unpack_kwargs":false,"variables":[]},{".class":"CallableType","arg_kinds":[0,0,0,0,1,1,1,1,1],"arg_names":["self","display_name","main","memory","version","description","subdomain","start","auto_restart"],"arg_types":["squarecloud.utils.ConfigFile","builtins.str","builtins.str","builtins.int",{".class":"UnionType","items":[{".class":"LiteralType","fallback":"builtins.str","value":"recommended"},{".class":"LiteralType","fallback":"builtins.str","value":"latest"}],"uses_pep604_syntax":false},{".class":"UnionType","items":["builtins.str",{".class":"NoneType"}],"uses_pep604_syntax":true},{".class":"UnionType","items":["builtins.str",{".class":"NoneType"}],"uses_pep604_syntax":true},{".class":"UnionType","items":["builtins.str",{".class":"NoneType"}],"uses_pep604_syntax":true},"builtins.bool"],"bound_args":[],"def_extras":{"first_arg":"self"},"fallback":"builtins.function","from_concatenate":false,"implicit":false,"imprecise_arg_kinds":false,"is_ellipsis_args":false,"name":"__init__ of ConfigFile","ret_type":{".class":"NoneType"},"type_guard":null,"type_is":null,"unpack_kwargs":false,"variables":[]}],"uses_pep604_syntax":false}}}},"__repr__":{".class":"SymbolTableNode","kind":"Mdef","node":{".class":"FuncDef","abstract_status":0,"arg_kinds":[0],"arg_names":[null],"dataclass_transform_spec":null,"flags":[],"fullname":"squarecloud.utils.ConfigFile.__repr__","name":"__repr__","type":{".class":"CallableType","arg_kinds":[0],"arg_names":[null],"arg_types":["squarecloud.utils.ConfigFile"],"bound_args":[],"def_extras":{"first_arg":"self"},"fallback":"builtins.function","from_concatenate":false,"implicit":false,"imprecise_arg_kinds":false,"is_ellipsis_args":false,"name":"__repr__ of ConfigFile","ret_type":"builtins.str","type_guard":null,"type_is":null,"unpack_kwargs":false,"variables":[]}}},"auto_restart":{".class":"SymbolTableNode","implicit":true,"kind":"Mdef","node":{".class":"Var","flags":["is_inferred"],"fullname":"squarecloud.utils.ConfigFile.auto_restart","name":"auto_restart","type":"builtins.bool"}},"content":{".class":"SymbolTableNode","kind":"Mdef","node":{".class":"FuncDef","abstract_status":0,"arg_kinds":[0],"arg_names":["self"],"dataclass_transform_spec":null,"flags":[],"fullname":"squarecloud.utils.ConfigFile.content","name":"content","type":{".class":"CallableType","arg_kinds":[0],"arg_names":["self"],"arg_types":["squarecloud.utils.ConfigFile"],"bound_args":[],"def_extras":{"first_arg":"self"},"fallback":"builtins.function","from_concatenate":false,"implicit":false,"imprecise_arg_kinds":false,"is_ellipsis_args":false,"name":"content of ConfigFile","ret_type":"builtins.str","type_guard":null,"type_is":null,"unpack_kwargs":false,"variables":[]}}},"description":{".class":"SymbolTableNode","implicit":true,"kind":"Mdef","node":{".class":"Var","flags":["is_inferred"],"fullname":"squarecloud.utils.ConfigFile.description","name":"description","type":{".class":"UnionType","items":["builtins.str",{".class":"NoneType"}],"uses_pep604_syntax":true}}},"display_name":{".class":"SymbolTableNode","implicit":true,"kind":"Mdef","node":{".class":"Var","flags":["is_inferred"],"fullname":"squarecloud.utils.ConfigFile.display_name","name":"display_name","type":"builtins.str"}},"from_dict":{".class":"SymbolTableNode","kind":"Mdef","node":{".class":"Decorator","func":{".class":"FuncDef","abstract_status":0,"arg_kinds":[0,0],"arg_names":["cls","dictionary"],"dataclass_transform_spec":null,"flags":["is_class","is_decorated"],"fullname":"squarecloud.utils.ConfigFile.from_dict","name":"from_dict","type":{".class":"CallableType","arg_kinds":[0,0],"arg_names":["cls","dictionary"],"arg_types":[{".class":"TypeType","item":"squarecloud.utils.ConfigFile"},{".class":"Instance","args":["builtins.str",{".class":"AnyType","missing_import_name":null,"source_any":null,"type_of_any":2}],"extra_attrs":null,"type_ref":"builtins.dict"}],"bound_args":[],"def_extras":{"first_arg":"cls"},"fallback":"builtins.function","from_concatenate":false,"implicit":false,"imprecise_arg_kinds":false,"is_ellipsis_args":false,"name":"from_dict of ConfigFile","ret_type":"squarecloud.utils.ConfigFile","type_guard":null,"type_is":null,"unpack_kwargs":false,"variables":[]}},"is_overload":false,"var":{".class":"Var","flags":["is_initialized_in_class","is_classmethod","is_ready","is_inferred"],"fullname":"squarecloud.utils.ConfigFile.from_dict","name":"from_dict","type":{".class":"CallableType","arg_kinds":[0,0],"arg_names":["cls","dictionary"],"arg_types":[{".class":"TypeType","item":"squarecloud.utils.ConfigFile"},{".class":"Instance","args":["builtins.str",{".class":"AnyType","missing_import_name":null,"source_any":null,"type_of_any":2}],"extra_attrs":null,"type_ref":"builtins.dict"}],"bound_args":[],"def_extras":{"first_arg":"cls"},"fallback":"builtins.function","from_concatenate":false,"implicit":false,"imprecise_arg_kinds":false,"is_ellipsis_args":false,"name":"from_dict of ConfigFile","ret_type":"squarecloud.utils.ConfigFile","type_guard":null,"type_is":null,"unpack_kwargs":false,"variables":[]}}}},"from_str":{".class":"SymbolTableNode","kind":"Mdef","node":{".class":"Decorator","func":{".class":"FuncDef","abstract_status":0,"arg_kinds":[0,0],"arg_names":["cls","content"],"dataclass_transform_spec":null,"flags":["is_class","is_decorated"],"fullname":"squarecloud.utils.ConfigFile.from_str","name":"from_str","type":{".class":"CallableType","arg_kinds":[0,0],"arg_names":["cls","content"],"arg_types":[{".class":"TypeType","item":"squarecloud.utils.ConfigFile"},"builtins.str"],"bound_args":[],"def_extras":{"first_arg":"cls"},"fallback":"builtins.function","from_concatenate":false,"implicit":false,"imprecise_arg_kinds":false,"is_ellipsis_args":false,"name":"from_str of ConfigFile","ret_type":"squarecloud.utils.ConfigFile","type_guard":null,"type_is":null,"unpack_kwargs":false,"variables":[]}},"is_overload":false,"var":{".class":"Var","flags":["is_initialized_in_class","is_classmethod","is_ready","is_inferred"],"fullname":"squarecloud.utils.ConfigFile.from_str","name":"from_str","type":{".class":"CallableType","arg_kinds":[0,0],"arg_names":["cls","content"],"arg_types":[{".class":"TypeType","item":"squarecloud.utils.ConfigFile"},"builtins.str"],"bound_args":[],"def_extras":{"first_arg":"cls"},"fallback":"builtins.function","from_concatenate":false,"implicit":false,"imprecise_arg_kinds":false,"is_ellipsis_args":false,"name":"from_str of ConfigFile","ret_type":"squarecloud.utils.ConfigFile","type_guard":null,"type_is":null,"unpack_kwargs":false,"variables":[]}}}},"main":{".class":"SymbolTableNode","implicit":true,"kind":"Mdef","node":{".class":"Var","flags":["is_inferred"],"fullname":"squarecloud.utils.ConfigFile.main","name":"main","type":"builtins.str"}},"memory":{".class":"SymbolTableNode","implicit":true,"kind":"Mdef","node":{".class":"Var","flags":["is_inferred"],"fullname":"squarecloud.utils.ConfigFile.memory","name":"memory","type":"builtins.int"}},"save":{".class":"SymbolTableNode","kind":"Mdef","node":{".class":"FuncDef","abstract_status":0,"arg_kinds":[0,1],"arg_names":["self","path"],"dataclass_transform_spec":null,"flags":[],"fullname":"squarecloud.utils.ConfigFile.save","name":"save","type":{".class":"CallableType","arg_kinds":[0,1],"arg_names":["self","path"],"arg_types":["squarecloud.utils.ConfigFile","builtins.str"],"bound_args":[],"def_extras":{"first_arg":"self"},"fallback":"builtins.function","from_concatenate":false,"implicit":false,"imprecise_arg_kinds":false,"is_ellipsis_args":false,"name":"save of ConfigFile","ret_type":{".class":"NoneType"},"type_guard":null,"type_is":null,"unpack_kwargs":false,"variables":[]}}},"start":{".class":"SymbolTableNode","implicit":true,"kind":"Mdef","node":{".class":"Var","flags":["is_inferred"],"fullname":"squarecloud.utils.ConfigFile.start","name":"start","type":{".class":"UnionType","items":["builtins.str",{".class":"NoneType"}],"uses_pep604_syntax":true}}},"subdomain":{".class":"SymbolTableNode","implicit":true,"kind":"Mdef","node":{".class":"Var","flags":["is_inferred"],"fullname":"squarecloud.utils.ConfigFile.subdomain","name":"subdomain","type":{".class":"UnionType","items":["builtins.str",{".class":"NoneType"}],"uses_pep604_syntax":true}}},"to_dict":{".class":"SymbolTableNode","kind":"Mdef","node":{".class":"FuncDef","abstract_status":0,"arg_kinds":[0],"arg_names":["self"],"dataclass_transform_spec":null,"flags":[],"fullname":"squarecloud.utils.ConfigFile.to_dict","name":"to_dict","type":{".class":"CallableType","arg_kinds":[0],"arg_names":["self"],"arg_types":["squarecloud.utils.ConfigFile"],"bound_args":[],"def_extras":{"first_arg":"self"},"fallback":"builtins.function","from_concatenate":false,"implicit":false,"imprecise_arg_kinds":false,"is_ellipsis_args":false,"name":"to_dict of ConfigFile","ret_type":{".class":"Instance","args":["builtins.str",{".class":"AnyType","missing_import_name":null,"source_any":null,"type_of_any":2}],"extra_attrs":null,"type_ref":"builtins.dict"},"type_guard":null,"type_is":null,"unpack_kwargs":false,"variables":[]}}},"version":{".class":"SymbolTableNode","implicit":true,"kind":"Mdef","node":{".class":"Var","flags":["is_inferred"],"fullname":"squarecloud.utils.ConfigFile.version","name":"version","type":{".class":"UnionType","items":[{".class":"LiteralType","fallback":"builtins.str","value":"recommended"},{".class":"LiteralType","fallback":"builtins.str","value":"latest"}],"uses_pep604_syntax":false}}}},"self_type":{".class":"TypeVarType","default":{".class":"AnyType","missing_import_name":null,"source_any":null,"type_of_any":4},"fullname":"squarecloud.utils.ConfigFile.Self","id":0,"name":"Self","namespace":"","upper_bound":"squarecloud.utils.ConfigFile","values":[],"variance":0},"slots":null,"tuple_type":null,"type_vars":[],"typeddict_type":null}},"Literal":{".class":"SymbolTableNode","cross_ref":"typing.Literal","kind":"Gdef","module_hidden":true,"module_public":false},"__annotations__":{".class":"SymbolTableNode","kind":"Gdef","node":{".class":"Var","flags":["is_ready"],"fullname":"squarecloud.utils.__annotations__","name":"__annotations__","type":{".class":"Instance","args":["builtins.str",{".class":"AnyType","missing_import_name":null,"source_any":null,"type_of_any":6}],"extra_attrs":null,"type_ref":"builtins.dict"}}},"__doc__":{".class":"SymbolTableNode","kind":"Gdef","node":{".class":"Var","flags":["is_ready"],"fullname":"squarecloud.utils.__doc__","name":"__doc__","type":"builtins.str"}},"__file__":{".class":"SymbolTableNode","kind":"Gdef","node":{".class":"Var","flags":["is_ready"],"fullname":"squarecloud.utils.__file__","name":"__file__","type":"builtins.str"}},"__name__":{".class":"SymbolTableNode","kind":"Gdef","node":{".class":"Var","flags":["is_ready"],"fullname":"squarecloud.utils.__name__","name":"__name__","type":"builtins.str"}},"__package__":{".class":"SymbolTableNode","kind":"Gdef","node":{".class":"Var","flags":["is_ready"],"fullname":"squarecloud.utils.__package__","name":"__package__","type":"builtins.str"}},"__spec__":{".class":"SymbolTableNode","kind":"Gdef","node":{".class":"Var","flags":["is_ready"],"fullname":"squarecloud.utils.__spec__","name":"__spec__","type":"importlib.machinery.ModuleSpec"}},"validate":{".class":"SymbolTableNode","cross_ref":"squarecloud._internal.decorators.validate","kind":"Gdef","module_hidden":true,"module_public":false}},"path":"/home/robert/Documents/squarecloud/sdk-api-py/squarecloud/utils.py"}